collimator/__init__.py
collimator/_init.py
collimator/lazy_loader.py
collimator/logging.py
collimator/profiling.py
collimator/version.py
collimator/backend/__init__.py
collimator/backend/_torch.py
collimator/backend/backend.py
collimator/backend/backend.pyi
collimator/backend/ode_solver.py
collimator/backend/results_data.py
collimator/backend/typing.py
collimator/backend/utils.py
collimator/backend/_jax/__init__.py
collimator/backend/_jax/bdf.py
collimator/backend/_jax/dopri5.py
collimator/backend/_jax/ode_solver.py
collimator/backend/_jax/ode_solver_impl.py
collimator/backend/_jax/python_functions.py
collimator/backend/_jax/results_data.py
collimator/backend/_jax/rk4.py
collimator/backend/_numpy/__init__.py
collimator/backend/_numpy/ode_solver.py
collimator/backend/_numpy/python_functions.py
collimator/backend/_numpy/results_data.py
collimator/cli/__init__.py
collimator/cli/cli_run.py
collimator/cli/collimator_cli.py
collimator/cli/model_interface.py
collimator/cli/run_fit_sindy.py
collimator/cli/run_optimization.py
collimator/cli/run_wildcat.py
collimator/dashboard/__init__.py
collimator/dashboard/api.py
collimator/dashboard/ensemble.py
collimator/dashboard/model.py
collimator/dashboard/project.py
collimator/dashboard/results.py
collimator/dashboard/schemas.py
collimator/dashboard/uiprops.py
collimator/dashboard/utils.py
collimator/dashboard/serialization/__init__.py
collimator/dashboard/serialization/block_interface.py
collimator/dashboard/serialization/from_model_json.py
collimator/dashboard/serialization/json_array.py
collimator/dashboard/serialization/model_json.py
collimator/dashboard/serialization/time_mode.py
collimator/dashboard/serialization/to_model_json.py
collimator/dashboard/serialization/ui_types.py
collimator/experimental/__init__.py
collimator/experimental/acausal/__init__.py
collimator/experimental/acausal/acausal_compiler.py
collimator/experimental/acausal/acausal_diagram.py
collimator/experimental/acausal/diagram_processing.py
pycollimator-2.2.0.dist-info/licenses/LICENSE.header.txt
pycollimator-2.2.0.dist-info/licenses/LICENSE.md
pycollimator-2.2.0.dist-info/METADATA
pycollimator-2.2.0.dist-info/WHEEL
pycollimator-2.2.0.dist-info/entry_points.txt
pycollimator-2.2.0.dist-info/top_level.txt
pycollimator-2.2.0.dist-info/RECORD
